{
  "appKey": "",
  "appSecret": "",
  "excludeScenes": [],
  "includeAnySDK": false,
  "inlineSpriteFrames": true,
  "inlineSpriteFrames_native": true,
  "mergeStartScene": false,
  "oauthLoginServer": "",
  "optimizeHotUpdate": false,
  "orientation": {
    "landscapeLeft": false,
    "landscapeRight": false,
    "portrait": true,
    "upsideDown": true
  },
  "packageName": "org.cocos2d.chat_client",
  "privateKey": "",
  "renderMode": "0",
  "startScene": "abd3084d-9d88-4a51-a307-15364438eef0",
  "title": "chat_client",
  "webOrientation": "auto",
  "includeSdk": [
    "anysdk"
  ]
}